{
    "version": "0.2",
    "dictionaries": [
        "html",
        "typescript",
        "css",
        "npm",
        "en-gb",
        "softwareTerms",
        "en_US",
        "powershell",
        "bash"
    ],
    "ignorePaths": [
        ".git/**",
        ".husky/**",
        ".gitignore",
        "**/*.eot",
        "**/*.ttf",
        "**/*.woff",
        "**/*.svg",
        ".nyc_output/**",
        "coverage/**",
        "doc/doc-template/static/scripts/prettify/**",
        "test/**",
        "package-lock.json",
        "node_modules/**"
    ],
    "ignoreWords": [
        "en",
        "gb"
    ],
    "words": [
        "ˈspɛk",
        "Anolis",
        "appmanifest",
        "classname",
        "defaultvalue",
        "defaultvaluetype",
        "deniak",
        "denodeify",
        "dests",
        "DNOTE",
        "Doclet",
        "doclets",
        "doop",
        "ENCODEDSOURCE",
        "flaticon",
        "foodoc",
        "globalobj",
        "googlecode",
        "hardwrap",
        "hellip",
        "htmlsafe",
        "iefix",
        "insafe",
        "Insafe",
        "ɪˈkɪd",
        "Jérémie",
        "lcov",
        "ldapauth",
        "ldapjs",
        "ldaps",
        "linenumber",
        "linenums",
        "linkto",
        "Ljmy",
        "longname",
        "mainpage",
        "mainpagetitle",
        "mkdir",
        "nodesecurity",
        "npmjs",
        "octo",
        "octokat",
        "Octokat",
        "octokit",
        "opentype",
        "originalname",
        "outdir",
        "Outfile",
        "outpath",
        "Plainicon",
        "plusplus",
        "pubrules",
        "PUBSYSTEM",
        "rarr",
        "rectalogic",
        "rectrack",
        "Remarkise",
        "REPLYTO",
        "respec",
        "sanslight",
        "sansregular",
        "sbin",
        "shortlink",
        "shortpath",
        "signup",
        "Spec'fully",
        "specberus",
        "specversion",
        "subparams",
        "subprops",
        "Subsetting",
        "Symfony",
        "Systeam",
        "taffydb",
        "testserver",
        "TR",
        "travisci",
        "tripu",
        "trstaging",
        "tutoriallink",
        "typedefs",
        "uuidv",
        "vulns",
        "webfont"
    ],
    "enableFiletypes": [
        "tmpl"
    ]
}
